pycounts_s_mck/__init__.py
pycounts_s_mck/plotting.py
pycounts_s_mck/pycounts_s_mck.py
pycounts_s_mck-0.1.0.dist-info/LICENSE
pycounts_s_mck-0.1.0.dist-info/METADATA
pycounts_s_mck-0.1.0.dist-info/WHEEL
pycounts_s_mck-0.1.0.dist-info/RECORD
