Metadata-Version: 2.1
Name: pycounts_s_mck
Version: 0.1.0
Summary: A package for counting the number of words in a text file
License: MIT
Author: Scout McKee
Requires-Python: >=3.9
Classifier: License :: OSI Approved :: MIT License
Classifier: Programming Language :: Python :: 3
Classifier: Programming Language :: Python :: 3.9
Classifier: Programming Language :: Python :: 3.10
Classifier: Programming Language :: Python :: 3.11
Classifier: Programming Language :: Python :: 3.12
Requires-Dist: matplotlib (>=3.4.3)
